dev_tools/__init__.py
dev_tools/dev_tools_api.py
dev_tools/aws/__init__.py
dev_tools/aws/get_s3_client.py
dev_tools/aws/upload_file.py
dev_tools/java/__init__.py
dev_tools/java/gradle_task.py
dev_tools/utils/__init__.py
dev_tools/utils/exec_cmd.py
dev_tools/utils/extract_archive.py
dev_tools/utils/find_paths.py
dev_tools/utils/format_path.py
dev_tools/utils/get_arch_name.py
dev_tools/utils/get_git_tag.py
dev_tools/utils/get_sha256.py
dev_tools/utils/make_archive.py
dev_tools/utils/read_file.py
dev_tools/utils/read_url_as_json.py
dev_tools/utils/silent_copy.py
dev_tools/utils/silent_remove.py
dev_tools/utils/write_file.py
hardfight_devtools-0.6.dist-info/LICENSE.txt
hardfight_devtools-0.6.dist-info/METADATA
hardfight_devtools-0.6.dist-info/WHEEL
hardfight_devtools-0.6.dist-info/top_level.txt
hardfight_devtools-0.6.dist-info/RECORD
