Metadata-Version: 2.1
Name: hardfight-devtools
Version: 0.6
Summary: Devtools is a Python utils tools to make building, testing and deploying hardfight projects easy
Home-page: https://github.com/Hardfight-Team/Hardfight-Devtools
Author: Eliot Maurice
Author-email: procyx.io@gmail.com
License: MIT
Keywords: hardfight,build,test,script
Platform: UNKNOWN
Classifier: Development Status :: 5 - Production/Stable
Classifier: Intended Audience :: Developers
Classifier: Topic :: Software Development :: Build Tools
Classifier: License :: OSI Approved :: MIT License
Classifier: Programming Language :: Python :: 3.7
Requires-Python: >=3.7, <4
License-File: LICENSE.txt
Requires-Dist: checksumdir
Requires-Dist: boto3
